fastapi_databoard/__init__.py
fastapi_databoard/config.py
fastapi_databoard/database.py
fastapi_databoard/databoard.py
fastapi_databoard/models.py
fastapi_databoard/templates/dashboard.html
fastapi_databoard-0.1.0.dist-info/METADATA
fastapi_databoard-0.1.0.dist-info/WHEEL
fastapi_databoard-0.1.0.dist-info/top_level.txt
fastapi_databoard-0.1.0.dist-info/RECORD
