Metadata-Version: 2.4
Name: fastapi-databoard
Version: 0.1.0
Summary: A database administration dashboard for FastAPI applications
Home-page: https://github.com/Bittu2903/fastapi-databoard
Author: Your Name
Author-email: Bittu Singh <bittusinghtech@gmail.com>
License: MIT
Project-URL: Homepage, https://github.com/Bittu2903/fastapi-databoard
Project-URL: Documentation, https://github.com/Bittu2903/fastapi-databoard#readme
Project-URL: Repository, https://github.com/Bittu2903/fastapi-databoard
Project-URL: Bug Tracker, https://github.com/Bittu2903/fastapi-databoard/issues
Keywords: fastapi,admin,dashboard,database,sqlalchemy,crud
Classifier: Development Status :: 3 - Alpha
Classifier: Intended Audience :: Developers
Classifier: Topic :: Software Development :: Libraries :: Python Modules
Classifier: License :: OSI Approved :: MIT License
Classifier: Programming Language :: Python :: 3
Classifier: Programming Language :: Python :: 3.8
Classifier: Programming Language :: Python :: 3.9
Classifier: Programming Language :: Python :: 3.10
Classifier: Programming Language :: Python :: 3.11
Classifier: Programming Language :: Python :: 3.12
Classifier: Framework :: FastAPI
Requires-Python: >=3.8
Requires-Dist: fastapi>=0.100.0
Requires-Dist: sqlalchemy>=2.0.0
Requires-Dist: pydantic>=2.0.0
Requires-Dist: jinja2>=3.0.0
Provides-Extra: async
Requires-Dist: asyncpg>=0.27.0; extra == "async"
Provides-Extra: postgres
Requires-Dist: psycopg2-binary>=2.9.0; extra == "postgres"
Provides-Extra: dev
Requires-Dist: pytest>=7.0.0; extra == "dev"
Requires-Dist: pytest-asyncio>=0.21.0; extra == "dev"
Requires-Dist: black>=23.0.0; extra == "dev"
Requires-Dist: flake8>=6.0.0; extra == "dev"
Requires-Dist: uvicorn>=0.23.0; extra == "dev"
Dynamic: author
Dynamic: home-page
Dynamic: requires-python
